dotprompt_cli/__init__.py
dotprompt_cli/gen.py
dotprompt_cli/gen.py.prompt
dotprompt_cli/models.py
dotprompt_cli/models.py.prompt
dotprompt_cli-0.0.4.dist-info/LICENSE
dotprompt_cli-0.0.4.dist-info/METADATA
dotprompt_cli-0.0.4.dist-info/WHEEL
dotprompt_cli-0.0.4.dist-info/entry_points.txt
dotprompt_cli-0.0.4.dist-info/RECORD
