Metadata-Version: 2.1
Name: dotprompt-cli
Version: 0.0.4
Summary: Generate files from AI prompts
License: MIT
Author: Dmitry Degtyarev
Author-email: ddegtyarev@gmail.com
Requires-Python: >=3.8,<4.0
Classifier: License :: OSI Approved :: MIT License
Classifier: Programming Language :: Python :: 3
Classifier: Programming Language :: Python :: 3.8
Classifier: Programming Language :: Python :: 3.9
Classifier: Programming Language :: Python :: 3.10
Classifier: Programming Language :: Python :: 3.11
Classifier: Programming Language :: Python :: 3.12
Requires-Dist: click (>=8.0.0,<9.0.0)
Requires-Dist: langchain-anthropic (>=0.1.17,<0.2.0)
Requires-Dist: langchain-aws (>=0.1.8,<0.2.0)
